sops_checker/__init__.py
sops_checker/__main__.py
sops_checker/cli.py
sops_checker-0.2.0.dist-info/METADATA
sops_checker-0.2.0.dist-info/WHEEL
sops_checker-0.2.0.dist-info/entry_points.txt
sops_checker-0.2.0.dist-info/licenses/LICENSE
sops_checker-0.2.0.dist-info/RECORD
