Metadata-Version: 2.4
Name: sops-checker
Version: 0.2.0
Summary: Validate that files matched by .sops.yaml creation_rules are SOPS-encrypted.
Project-URL: Homepage, https://github.com/psvmcc/sops-checker
Project-URL: Bug Tracker, https://github.com/psvmcc/sops-checker/issues
Project-URL: Changelog, https://github.com/psvmcc/sops-checker/releases
Author: Sergey Putko
License: MIT License
License-File: LICENSE
Keywords: cli,devsecops,encryption,sops
Classifier: Development Status :: 3 - Alpha
Classifier: Environment :: Console
Classifier: Intended Audience :: Developers
Classifier: License :: OSI Approved :: MIT License
Classifier: Programming Language :: Python :: 3
Classifier: Programming Language :: Python :: 3.8
Classifier: Programming Language :: Python :: 3.9
Classifier: Programming Language :: Python :: 3.10
Classifier: Programming Language :: Python :: 3.11
Classifier: Programming Language :: Python :: 3.12
Classifier: Programming Language :: Python :: 3.13
Classifier: Programming Language :: Python :: 3.14
Classifier: Topic :: Security :: Cryptography
Requires-Python: >=3.8
Requires-Dist: pyyaml>=6.0
Provides-Extra: dev
Requires-Dist: pytest>=8.3.5; extra == 'dev'
Requires-Dist: ruff>=0.5.0; extra == 'dev'
Requires-Dist: yamllint>=1.35.0; extra == 'dev'
